{
    "carga_horaria_total": "Não informado",
    "co_requisitos": "-",
    "codigo": "01",
    "codigo_componente": "DIN0041",
    "disciplina": "DIN0041 - PROGRAMACAO VISUAL 2",
    "docente": "24",
    "ementa": "Ementa:Desenvolvimento de projetos de média complexidade em Programação Visual.Objetivos:  1. Objetivo atitudinal: estimular e desenvolver a sensibilidade, o senso crítico, e a capacidade de interação em equipes multidisciplinares, de modo que sejam capazes de compreender o projeto como a síntese de visão e ação mais abrangentes e contextualizadas do design na economia, na cultura e na sociedade.2. Objetivo de processo: desenvolver a prática projetual em design, isto é, exercitar a capacidade de conceber soluções em design através de um processo ordenado, contínuo e acumulativo de pesquisa, análise, reelaboração e síntese conceitual e formal.3. Objetivo de conteúdo: capacitar o aluno a desenvolver projetos sistematizados de média complexidade em programação visual de modo que venha a compreender a idéia de marca e identidade de marca, aplicadas no âmbito de organizações públicas ou privadas.",
    "equivalencias": "-",
    "excluir_avaliacao": "Não",
    "horario": "4M12345 4T1 Quarta-feira 08:00 às 13:50",
    "horario_flexivel": "Não",
    "local": "",
    "matriculavel_online": "Sim",
    "modalidade_educacao": "Presencial",
    "nome_componente": "PROGRAMACAO VISUAL 2",
    "permite_multiplas_aprovacoes": "Não",
    "pre_requisitos": "( ( DIN0040 ) )",
    "quantidade_avaliacoes": "1",
    "tipo_componente": "DISCIPLINA",
    "turma": "GEORGIA MARIA DE CASTRO SANTOS (90h) ANA MANSUR DE OLIVEIRA (90h)",
    "unidade_responsavel": "DEPARTAMENTO DE DESIGN (11.01.01.14.04) - BRASÍLIA - 11.01.01.14.04"
}