{
    "carga_horaria_total": "Não informado",
    "co_requisitos": "-",
    "codigo": "01",
    "codigo_componente": "IFD0017",
    "disciplina": "IFD0017 - FÍSICA MATEMÁTICA A",
    "docente": "40",
    "ementa": "Sequências infinitas, séries e séries de funções. Equações diferenciais ordinárias. Equações diferenciais parciais e separação de variáveis. Teoria de Sturm-Liouville efunções ortogonais. Funções especiais. Séries de Fourier. Equações diferenciais parciais. Equações do calor, de onda e de Laplace. Transformadas integrais. Transformada de Fourier e de Laplace. Funçõesde Green. Distribuições",
    "equivalencias": "-",
    "excluir_avaliacao": "Não",
    "horario": "35M34 Terça-feira 10:00 às 11:50Quinta-feira 10:00 às 11:50",
    "horario_flexivel": "Não",
    "local": "",
    "matriculavel_online": "Sim",
    "modalidade_educacao": "Presencial",
    "nome_componente": "FÍSICA MATEMÁTICA A",
    "permite_multiplas_aprovacoes": "Não",
    "pre_requisitos": "( ( MAT0028 ) E ( MAT0039 OU MAT0031 ) OU ( IFD0012 E MAT0026 ) )",
    "quantidade_avaliacoes": "1",
    "tipo_componente": "DISCIPLINA",
    "turma": "ALEKSANDR NIKOLAIEVICH PINZUL (60h)",
    "unidade_responsavel": "INSTITUTO DE FÍSICA - BRASÍLIA - 11.01.01.16"
}