{
    "carga_horaria_total": "Não informado",
    "co_requisitos": "-",
    "codigo": "02",
    "codigo_componente": "Ano.Período de Implementação",
    "disciplina": "ECO0093 - SEMINARIO DE POLITICA FISCAL",
    "docente": "10",
    "ementa": "Disciplina de seminários em Política Fiscal, cujos temas serão definidos no semestre corrente.",
    "equivalencias": "( ECO0091 ) OU ( ECO0092 )",
    "excluir_avaliacao": "Não",
    "horario": "2T23 Segunda-feira 14:00 às 15:50",
    "horario_flexivel": "Não",
    "local": "",
    "matriculavel_online": "Sim",
    "modalidade_educacao": "Presencial",
    "nome_componente": "SEMINARIO DE POLITICA FISCAL",
    "permite_multiplas_aprovacoes": "Não",
    "pre_requisitos": "( ( ECO0126 E ECO0099 ) )",
    "quantidade_avaliacoes": "1",
    "tipo_componente": "DISCIPLINA",
    "turma": "MAURICIO SOARES BUGARIN (30h)",
    "unidade_responsavel": "DEPTO ECONOMIA - BRASÍLIA - 11.01.01.02.03"
}