{
    "carga_horaria_total": "Não informado",
    "co_requisitos": "-",
    "codigo": "02",
    "codigo_componente": "FDD0282",
    "disciplina": "FDD0282 - FUNDAMENTOS DO DIREITO AMBIENTAL",
    "docente": "40",
    "ementa": "Bem jurídico ambiental e evolução histórica do pensamento jus ambiental. Direito do Ambiente: conceito, princípios, objeto, instrumentos legais. Tutela constitucional ambiental. Política Nacional do Meio Ambiente. Espaços ambientalmente protegidos. Recursos hídricos. Tutela administrativa do ambiente: poder de polícia, competência, licenciamento (EIA/RIMA), responsabilidade administrativa. Tutela e responsabilidade civil do ambiente. Aspectos processuais da proteção ambiental. Papel da sociedade civil e os mecanismos de participação popular na proteção do ambiente. Noções gerais da tutela penal do ambiente.",
    "equivalencias": "-",
    "excluir_avaliacao": "Não",
    "horario": "35N34 Terça-feira 20:50 às 22:30Quinta-feira 20:50 às 22:30",
    "horario_flexivel": "Não",
    "local": "",
    "matriculavel_online": "Sim",
    "modalidade_educacao": "Presencial",
    "nome_componente": "FUNDAMENTOS DO DIREITO AMBIENTAL",
    "permite_multiplas_aprovacoes": "Não",
    "pre_requisitos": "( ( ECO0262 ) OU ( ECO0261 ) OU ( ENC0002 ) )",
    "quantidade_avaliacoes": "1",
    "tipo_componente": "DISCIPLINA",
    "turma": "JEFFERSON CRESCENCIO NERI (60h)",
    "unidade_responsavel": "FACULDADE DE DIREITO - BRASÍLIA - 11.01.01.06"
}