{
    "carga_horaria_total": "Não informado",
    "co_requisitos": "-",
    "codigo": "01",
    "codigo_componente": "Ano.Período de Implementação",
    "disciplina": "LET0055 - CIVILIZACAO FRANCESA",
    "docente": "30",
    "ementa": "Apresentação da França. A geografia física, econômica e humana: as grandes regiões naturais e econômicas. A história: as grandes etapas da civilização francesa dos celtas aos nossos dias constituição do domínio nacional, sucessão cronólogica das principais sociedades, dinastias, regimes políticos.",
    "equivalencias": "( ( LET0061 ) )",
    "excluir_avaliacao": "Não",
    "horario": "24M12 Segunda-feira 08:00 às 09:50Quarta-feira 08:00 às 09:50",
    "horario_flexivel": "Não",
    "local": "",
    "matriculavel_online": "Sim",
    "modalidade_educacao": "Presencial",
    "nome_componente": "CIVILIZACAO FRANCESA",
    "permite_multiplas_aprovacoes": "Não",
    "pre_requisitos": "( ( LET0324 ) OU ( LET0325 ) )",
    "quantidade_avaliacoes": "1",
    "tipo_componente": "DISCIPLINA",
    "turma": "ANNE LOUISE DIAS (60h)",
    "unidade_responsavel": "DEPTO LÍNGUAS ESTRANGEIRAS E TRADUÇÃO - BRASÍLIA - 11.01.01.19.01"
}