{
    "carga_horaria_total": "Não informado",
    "co_requisitos": "-",
    "codigo": "01",
    "codigo_componente": "FCE0255",
    "disciplina": "FCE0255 - DEONTOLOGIA E LEGISLAÇÃO FARMACÊUTICA",
    "docente": "50",
    "ementa": "Estrutura organizacional e jurídica da Profissão farmacêutica. Organização da profissão farmacêutica e sua atuação profissional na assistência farmacêutica. Legislação farmacêutica e sanitária.",
    "equivalencias": "( FAR0250 )",
    "excluir_avaliacao": "Não",
    "horario": "2M12 Segunda-feira 08:00 às 09:50",
    "horario_flexivel": "Não",
    "local": "",
    "matriculavel_online": "Sim",
    "modalidade_educacao": "Presencial",
    "nome_componente": "DEONTOLOGIA E LEGISLAÇÃO FARMACÊUTICA",
    "permite_multiplas_aprovacoes": "Não",
    "pre_requisitos": "( ( FCE0188 E FCE0213 ) OU ( FAR0119 ) )",
    "quantidade_avaliacoes": "1",
    "tipo_componente": "DISCIPLINA",
    "turma": "RINALDO EDUARDO MACHADO DE OLIVEIRA (30h)",
    "unidade_responsavel": "CAMPUS UNB CEILÂNDIA: FACULDADE DE CIENCIAS E TECNOLOGIAS EM SAÚDE - BRASÍLIA - 11.01.31"
}