{
    "carga_horaria_total": "Não informado",
    "co_requisitos": "-",
    "codigo": "01",
    "codigo_componente": "Ano.Período de Implementação",
    "disciplina": "IQD0451 - EMPREENDEDORISMO TECNOLÓGICO: PRINCÍPIOS E ESTRATÉGIAS PARA CRIAÇÃO SPIN-OFFS DEEPTECHS",
    "docente": "40",
    "ementa": "Capacitar os alunos para o empreendedorismo científico, com ênfase em inovação tecnológica e desenvolvimento de produtos. Também serão utilizadas atividades extensionistas que já constam na estrutura do curso para que sejam integralizadas executando atividades que incentivam a interação com ambientes de inovação, empresas, e a comunidade empreendedora, proporcionando uma experiência prática que conecta o conhecimento científico ao mercado.",
    "equivalencias": "-",
    "excluir_avaliacao": "Não",
    "horario": "6T45 Sexta-feira 16:00 às 17:50",
    "horario_flexivel": "Não",
    "local": "",
    "matriculavel_online": "Sim",
    "modalidade_educacao": "Presencial",
    "nome_componente": "EMPREENDEDORISMO TECNOLÓGICO: PRINCÍPIOS E ESTRATÉGIAS PARA CRIAÇÃO SPIN-OFFS DEEPTECHS",
    "permite_multiplas_aprovacoes": "Não",
    "pre_requisitos": "-",
    "quantidade_avaliacoes": "1",
    "tipo_componente": "DISCIPLINA",
    "turma": "MARCELO OLIVEIRA RODRIGUES (30h)",
    "unidade_responsavel": "INSTITUTO DE QUÍMICA - BRASÍLIA - 11.01.01.22"
}