{
    "carga_horaria_total": "Não informado",
    "co_requisitos": "-",
    "codigo": "02",
    "codigo_componente": "TEC0027",
    "disciplina": "TEC0027 - INFRA-ESTRUTURA URBANA",
    "docente": "26",
    "ementa": "Distribuição e  condicionantes dos Desenho Urbano. Infra-Estrutura de abastecimento de água, esgotamento sanitário, drenagem urbana, limpeza pública e de serviços de eletricidade. Sistemas convencionais e alternativos: avaliação dos custos de instalação e manutenção.",
    "equivalencias": "( FAU0249 )",
    "excluir_avaliacao": "Não",
    "horario": "6N12 Sexta-feira 19:00 às 20:40",
    "horario_flexivel": "Não",
    "local": "",
    "matriculavel_online": "Sim",
    "modalidade_educacao": "Presencial",
    "nome_componente": "INFRA-ESTRUTURA URBANA",
    "permite_multiplas_aprovacoes": "Não",
    "pre_requisitos": "-",
    "quantidade_avaliacoes": "1",
    "tipo_componente": "DISCIPLINA",
    "turma": "MARIA DO CARMO DE LIMA BEZERRA (30h) TATIANA MAMEDE SALUM CHAER (30h)",
    "unidade_responsavel": "DEPTO TECNOLOGIA ARQUITETURA URBANISMO - BRASÍLIA - 11.01.01.04.02"
}