{
    "carga_horaria_total": "Não informado",
    "co_requisitos": "-",
    "codigo": "02",
    "codigo_componente": "ADM0061",
    "disciplina": "ADM0061 - LOGÍSTICA ORGANIZACIONAL",
    "docente": "55",
    "ementa": "Fundamentos da Logística Empresarial. O Composto Logístico. Planejamento e controle Logístico. Atividades da Logística Empresarial. Cadeia de Suprimentos e Gerenciamento da Cadeia de Suprimentos. Operações. Previsão de Demanda. Gestão de Estoques. Distribuição. Armazenagem.Logística Reversa. Tópicos Emergentes de Logística.",
    "equivalencias": "( ADM0058 ) OU ( ADM0059 ) OU ( ADM0060 )",
    "excluir_avaliacao": "Não",
    "horario": "35N12 Terça-feira 19:00 às 20:40Quinta-feira 19:00 às 20:40",
    "horario_flexivel": "Não",
    "local": "",
    "matriculavel_online": "Sim",
    "modalidade_educacao": "Presencial",
    "nome_componente": "LOGÍSTICA ORGANIZACIONAL",
    "permite_multiplas_aprovacoes": "Não",
    "pre_requisitos": "( ( ADM0023 ) )",
    "quantidade_avaliacoes": "1",
    "tipo_componente": "DISCIPLINA",
    "turma": "ANA CAROLINA FERREIRA DE SIQUEIRA (60h)",
    "unidade_responsavel": "DEPTO ADMINISTRAÇÃO - BRASÍLIA - 11.01.01.02.01"
}