{
    "carga_horaria_total": "Não informado",
    "co_requisitos": "-",
    "codigo": "01",
    "codigo_componente": "CET0041",
    "disciplina": "CET0041 - CONSTRUÇÃO DO CONHECIMENTO CIENTÍFICO",
    "docente": "45",
    "ementa": "O caráter multidisciplinar do Turismo. Conhecimento científico: construção do conhecimento e processo de investigação em Turismo. Método, metodologia. Produção e apresentação de projetos e trabalhos científicos na área do Turismo.",
    "equivalencias": "-",
    "excluir_avaliacao": "Não",
    "horario": "4M1234 Quarta-feira 08:00 às 11:50",
    "horario_flexivel": "Não",
    "local": "",
    "matriculavel_online": "Sim",
    "modalidade_educacao": "Presencial",
    "nome_componente": "CONSTRUÇÃO DO CONHECIMENTO CIENTÍFICO",
    "permite_multiplas_aprovacoes": "Não",
    "pre_requisitos": "-",
    "quantidade_avaliacoes": "1",
    "tipo_componente": "DISCIPLINA",
    "turma": "MARUTSCHKA MARTINI MOESCH (60h)",
    "unidade_responsavel": "CENTRO DE EXCELÊNCIA EM TURISMO - BRASÍLIA - 11.01.18"
}