{
    "carga_horaria_total": "Não informado",
    "co_requisitos": "-",
    "codigo": "05",
    "codigo_componente": "Ano.Período de Implementação",
    "disciplina": "TEL0021 - LITERATURA BRASILEIRA - ROMANTISMO",
    "docente": "40",
    "ementa": "Romantismo: visão estética e condicionamento histórico. Influências estrangeiras. O significado do indío. Renovação estilistica.  A ficção romântica e a formação do romance brasileiro. A poesia romântica.",
    "equivalencias": "-",
    "excluir_avaliacao": "Não",
    "horario": "24T23 Segunda-feira 14:00 às 15:50Quarta-feira 14:00 às 15:50",
    "horario_flexivel": "Não",
    "local": "",
    "matriculavel_online": "Sim",
    "modalidade_educacao": "Presencial",
    "nome_componente": "LITERATURA BRASILEIRA - ROMANTISMO",
    "permite_multiplas_aprovacoes": "Não",
    "pre_requisitos": "-",
    "quantidade_avaliacoes": "1",
    "tipo_componente": "DISCIPLINA",
    "turma": "AUGUSTO RODRIGUES DA SILVA JUNIOR (30h) DANGLEI DE CASTRO PEREIRA (30h)",
    "unidade_responsavel": "DEPTO TEORIA LITERÁRIA E LITERATURA - BRASÍLIA - 11.01.01.19.03"
}