{
    "carga_horaria_total": "Não informado",
    "co_requisitos": "-",
    "codigo": "01",
    "codigo_componente": "Ano.Período de Implementação",
    "disciplina": "ODT0155 - SAÚDE BUCAL COLETIVA 1",
    "docente": "30",
    "ementa": "Essa é a primeira disciplina profissionalizante do conjunto de disciplinas que formam o corredor específico de formação em Saúde Bucal Coletiva para os alunos do curso de Odontologia. Essa disciplina se pauta nos conceitos de \"Saúde Coletiva\" \"trabalho em equipe\" \"ação\" \"desenvolvimento comunitário\" \"promoção da saúde\" \"vigilância à saúde\" \"rede de atenção\", \"atenção domiciliar\" e Equidade (formar uma consciência crítica em relação às questões étnico-raciais no Brasil e formar profissionais críticos e embasados teoricamente a respeito dos princípios gerais de educação inclusiva.",
    "equivalencias": "-",
    "excluir_avaliacao": "Não",
    "horario": "4M1234 Quarta-feira 08:00 às 11:50",
    "horario_flexivel": "Não",
    "local": "",
    "matriculavel_online": "Sim",
    "modalidade_educacao": "Presencial",
    "nome_componente": "SAÚDE BUCAL COLETIVA 1",
    "permite_multiplas_aprovacoes": "Não",
    "pre_requisitos": "( ( DSC0037 ) )",
    "quantidade_avaliacoes": "1",
    "tipo_componente": "DISCIPLINA",
    "turma": "GILBERTO ALFREDO PUCCA JUNIOR (30h) FABIO CARNEIRO MARTINS (30h)",
    "unidade_responsavel": "DEPTO ODONTOLOGIA - BRASÍLIA - 11.01.01.10.04"
}