{
    "carga_horaria_total": "Não informado",
    "co_requisitos": "-",
    "codigo": "01",
    "codigo_componente": "Ano.Período de Implementação",
    "disciplina": "LET0234 - ESTAGIO SUPERVISIONADO DE TRADUCAO-INGLES",
    "docente": "24",
    "ementa": "TRADUCAO DE TEXTOS COMPLETOS NAS DIVERSAS AREAS DO CONHECIMENTO,  SOBORIENTACAO DE UM PROFESSOR OU DE PROFISSIONAL DA AREA. A  ATIVIDADE SERADESENVOLVIDA EXTERNAMENTE OU ATRAVES DA OFICINA DE TRADUCAO.",
    "equivalencias": "( LET0233 )",
    "excluir_avaliacao": "Não",
    "horario": "356M5 356T1 Terça-feira 12:00 às 13:50Quinta-feira 12:00 às 13:50Sexta-feira 12:00 às 13:50",
    "horario_flexivel": "Não",
    "local": "",
    "matriculavel_online": "Sim",
    "modalidade_educacao": "Presencial",
    "nome_componente": "ESTAGIO SUPERVISIONADO DE TRADUCAO-INGLES",
    "permite_multiplas_aprovacoes": "Não",
    "pre_requisitos": "( ( LET0182 E LET0202 E LET0186 E LET0206 ) OU ( LET0190 E LET0210 ) )",
    "quantidade_avaliacoes": "1",
    "tipo_componente": "DISCIPLINA",
    "turma": "CAROLINA PEREIRA BARCELLOS (90h)",
    "unidade_responsavel": "DEPTO LÍNGUAS ESTRANGEIRAS E TRADUÇÃO - BRASÍLIA - 11.01.01.19.01"
}