{
    "carga_horaria_total": "Não informado",
    "co_requisitos": "-",
    "codigo": "01",
    "codigo_componente": "MUS0650",
    "disciplina": "MUS0650 - INTRODUCAO AO CANTO 2",
    "docente": "2",
    "ementa": "Estudo dos princípios básicos da Técnica vocal do canto lírico: preparação corporal, respiração e sustentação da voz, vocalização\r\ne ressonância, dicção. Aplicação da técnica vocal a um repertório de pequena dificuldade. Estudo orientado da interpretação do\r\nrepertório",
    "equivalencias": "( IDA0263 ) OU ( MUS0649 )",
    "excluir_avaliacao": "Não",
    "horario": "2N12 Segunda-feira 19:00 às 20:40",
    "horario_flexivel": "Não",
    "local": "",
    "matriculavel_online": "Sim",
    "modalidade_educacao": "Presencial",
    "nome_componente": "INTRODUCAO AO CANTO 2",
    "permite_multiplas_aprovacoes": "Não",
    "pre_requisitos": "( ( MUS0648 ) )",
    "quantidade_avaliacoes": "1",
    "tipo_componente": "DISCIPLINA",
    "turma": "ERIKA KALLINA FARIAS DE OLIVEIRA (30h)",
    "unidade_responsavel": "DEPTO MÚSICA - BRASÍLIA - 11.01.01.14.02"
}