{
    "carga_horaria_total": "Não informado",
    "co_requisitos": "-",
    "codigo": "02",
    "codigo_componente": "LET0260",
    "disciplina": "LET0260 - INGLES: EXPRESSAO ESCRITA 2",
    "docente": "35",
    "ementa": "Aspectos cognitivos e discursivos da escrita: as diversas modalidades de texto, introdução e desenvolvimento das duas principais tarefas envolvidas no processo de composiçãode um texto: a geração de ideias e sua transformação em texto, de acordo com os objetivos do escritor e as necessidades do leitor, prática de redação nas modalidades  \"informal/formal\": cartas, descrições e narrativas.",
    "equivalencias": "( LET0259 OU LET0765 )",
    "excluir_avaliacao": "Não",
    "horario": "35T23 Terça-feira 14:00 às 15:50Quinta-feira 14:00 às 15:50",
    "horario_flexivel": "Não",
    "local": "",
    "matriculavel_online": "Sim",
    "modalidade_educacao": "Presencial",
    "nome_componente": "INGLES: EXPRESSAO ESCRITA 2",
    "permite_multiplas_aprovacoes": "Não",
    "pre_requisitos": "( LET0262 OU LET0086 OU LET0764 )",
    "quantidade_avaliacoes": "1",
    "tipo_componente": "DISCIPLINA",
    "turma": "TATIANNE GOMES DE SOUSA (60h)",
    "unidade_responsavel": "DEPTO LÍNGUAS ESTRANGEIRAS E TRADUÇÃO - BRASÍLIA - 11.01.01.19.01"
}