{
    "carga_horaria_total": "Não informado",
    "co_requisitos": "-",
    "codigo": "01",
    "codigo_componente": "DIN0040",
    "disciplina": "DIN0040 - PROGRAMACAO VISUAL 1",
    "docente": "20",
    "ementa": "Ementa:Desenvolver o projeto de programação visual, com ênfase em projetos de baixa complexidade.Objetivos:\tDesenvolver a capacidade de projetar do aluno na área de programação visual, levando-o a compreender e projetar segundo as noções de sistema, organização e hierarquia de informações visuais.Específicos:Incentivar a intersecção dos processos criativos, de projeto e de linguagens presentes nas comunicações visuais, permitindo ao aluno desenvolver de forma sistêmica projetos iniciais em design.",
    "equivalencias": "-",
    "excluir_avaliacao": "Não",
    "horario": "2M12345 Segunda-feira 08:00 às 12:55",
    "horario_flexivel": "Não",
    "local": "",
    "matriculavel_online": "Sim",
    "modalidade_educacao": "Presencial",
    "nome_componente": "PROGRAMACAO VISUAL 1",
    "permite_multiplas_aprovacoes": "Não",
    "pre_requisitos": "( ( DIN0023 ) )",
    "quantidade_avaliacoes": "1",
    "tipo_componente": "DISCIPLINA",
    "turma": "MARISA COBBE MAASS (90h)",
    "unidade_responsavel": "DEPARTAMENTO DE DESIGN (11.01.01.14.04) - BRASÍLIA - 11.01.01.14.04"
}